{
  "entity.vehicle.collision": {
    "subtitle": "subtitles.motobox.collision",
    "sounds": [
      "motobox:collision"
    ]
  },
  "entity.vehicle.landing": {
    "subtitle": "subtitles.motobox.landing",
    "sounds": [
      "motobox:landing"
    ]
  },
  "entity.vehicle.skid": {
    "subtitle": "subtitles.motobox.skid",
    "sounds": [
      "motobox:skid"
    ]
  },
  "entity.vehicle.motorbike_engine": {
    "subtitle": "subtitles.motobox.vehicle_engine",
    "sounds": [
      "motobox:motorbike_engine"
    ]
  },
  "entity.vehicle.diesel_four_cylinder_engine": {
    "subtitle": "subtitles.motobox.vehicle_engine",
    "sounds": [
      "motobox:diesel_four_cylinder_engine"
    ]
  }
}